[
  {
    "name": "叶泯希",
    "url": "https://blog.418121.xyz/rss2.xml"
  },
  {
    "name": "茗辰原 の 异世界",
    "url": "https://mingcy.cn/atom.xml"
  },
  {
    "name": "清羽飞扬",
    "url": "https://blog.liushen.fun/atom.xml"
  },
  {
    "name": "Mete0r的虚拟小世界",
    "url": "https://www.xscnet.cn/atom.xml"
  },
  {
    "name": "钧言极客",
    "url": "https://www.jinjun.top/atom.xml"
  },
  {
    "name": "Handsome",
    "url": "https://www.lik.cc/rss.xml"
  },
  {
    "name": "葱苓语畔",
    "url": "https://blog.ciraos.top/atom.xml"
  },
  {
    "name": "张苹果",
    "url": "https://zhangpingguo.com/rss.xml"
  },
  {
    "name": "yuang01",
    "url": "https://hexo-theme-bamboo.netlify.app/atom.xml"
  },
  {
    "name": "周润发",
    "url": "https://blog.zrf.me/atom.xml"
  },
  {
    "name": "伍十七",
    "url": "https://blog.efu.me/rss.xml"
  },
  {
    "name": "糖菓·部落",
    "url": "https://candinya.com/atom.xml"
  },
  {
    "name": "青序栈",
    "url": "https://qxzhan.cn/feed"
  },
  {
    "name": "慕鸢のblog",
    "url": "https://www.muyuanhuck.cn/feed"
  }
]